azure/mgmt/operationsmanagement/__init__.py
azure/mgmt/operationsmanagement/_configuration.py
azure/mgmt/operationsmanagement/_operations_management_client.py
azure/mgmt/operationsmanagement/_version.py
azure/mgmt/operationsmanagement/aio/__init__.py
azure/mgmt/operationsmanagement/aio/_configuration.py
azure/mgmt/operationsmanagement/aio/_operations_management_client.py
azure/mgmt/operationsmanagement/aio/operations/__init__.py
azure/mgmt/operationsmanagement/aio/operations/_management_associations_operations.py
azure/mgmt/operationsmanagement/aio/operations/_management_configurations_operations.py
azure/mgmt/operationsmanagement/aio/operations/_operations.py
azure/mgmt/operationsmanagement/aio/operations/_solutions_operations.py
azure/mgmt/operationsmanagement/models/__init__.py
azure/mgmt/operationsmanagement/models/_models.py
azure/mgmt/operationsmanagement/models/_models_py3.py
azure/mgmt/operationsmanagement/operations/__init__.py
azure/mgmt/operationsmanagement/operations/_management_associations_operations.py
azure/mgmt/operationsmanagement/operations/_management_configurations_operations.py
azure/mgmt/operationsmanagement/operations/_operations.py
azure/mgmt/operationsmanagement/operations/_solutions_operations.py
azure_mgmt_operationsmanagement-1.0.0.dist-info/METADATA
azure_mgmt_operationsmanagement-1.0.0.dist-info/WHEEL
azure_mgmt_operationsmanagement-1.0.0.dist-info/top_level.txt
azure_mgmt_operationsmanagement-1.0.0.dist-info/RECORD
